{
    "denuncia": [
        {
            "denunciante": "2b6b0204-edcf-4963-9562-b9d3ff07641d",
            "denunciado": "3f988b44-a034-45e0-9e6b-07b949b28b74",
            "descricao": "Vendedor não enviou o produto."
        },
        {
            "denunciante": "3f988b44-a034-45e0-9e6b-07b949b28b74",
            "denunciado": "04017639-688d-4a1d-a99b-d7b686259048",
            "descricao": "Vendedora caloteira!!!!!!!!!"
        }
    ],
    "avaliacao": [
        {
            "cod_avaliador": "3f988b44-a034-45e0-9e6b-07b949b28b74",
            "cod_avaliado": "2b6b0204-edcf-4963-9562-b9d3ff07641d",
            "nota": 5,
            "descricao": "CD de ótima qualidade, vendedor atencioso e entrega rápida. Vibrei tanto com a música que minha mãe ficou com medo"
        },
        {
            "cod_avaliador": "2b6b0204-edcf-4963-9562-b9d3ff07641d",
            "cod_avaliado": "3f988b44-a034-45e0-9e6b-07b949b28b74",
            "nota": 4,
            "descricao": "Ótimo CD, mas a entrega demorou um pouco mais do que o esperado. Recomendo!"
        },
        {
            "cod_avaliador": "04017639-688d-4a1d-a99b-d7b686259048",
            "cod_avaliado": "2b6b0204-edcf-4963-9562-b9d3ff07641d",
            "nota": 3,
            "descricao": "CD bom, mas não atendeu totalmente às minhas expectativas. A música é boa, mas poderia ser melhor."
        }
    ],
    "carrinho_disco": [
        {
            "cod_usuario": "3f988b44-a034-45e0-9e6b-07b949b28b74",
            "id_prod": "136359f1-332e-4b71-a83a-d6af5d42b919"
        },
        {
            "cod_usuario": "3f988b44-a034-45e0-9e6b-07b949b28b74",
            "id_prod": "5b26715b-b98a-4c28-971c-79c8d5006b5f"
        }
    ],
    "carrinho_livro": [
        {
            "cod_usuario": "3f988b44-a034-45e0-9e6b-07b949b28b74",
            "id_prod": "f51953ce-0c1f-4ffb-8f3a-592f036720d2"
        },
        {
            "cod_usuario": "2b6b0204-edcf-4963-9562-b9d3ff07641d",
            "id_prod": "b8f4133f-9118-4a94-b258-29471138883b"
        }
    ],
    "desejos_livro": [
        {
            "cod_usuario": "3f988b44-a034-45e0-9e6b-07b949b28b74",
            "id_prod": "f51953ce-0c1f-4ffb-8f3a-592f036720d2"
        },
        {
            "cod_usuario": "2b6b0204-edcf-4963-9562-b9d3ff07641d",
            "id_prod": "6d729e2f-515a-471a-85d2-06858e5d0a64"
        }
    ],
    "desejos_disco": [
        {
            "cod_usuario": "3f988b44-a034-45e0-9e6b-07b949b28b74",
            "id_prod": "136359f1-332e-4b71-a83a-d6af5d42b919"
        },
        {
            "cod_usuario": "2b6b0204-edcf-4963-9562-b9d3ff07641d",
            "id_prod": "0f63ff4e-73e4-4a29-b611-3968e0d68800"
        }
    ],
    "disco": [
        {
            "id_prod": "0f63ff4e-73e4-4a29-b611-3968e0d68800",
            "id_usuario": "8f3075c3-b45b-432a-a9e9-0639d73d63c4",
            "nome": "A Day At The Races - CD",
            "valor": 6540,
            "condicao": "Ótimo",
            "descricao": "CD do álbum da banda Queen, remaster de 2011",
            "artista": "Queen",
            "ano": 2011,
            "gravadora": "EMI"
        },
        {
            "id_prod": "136359f1-332e-4b71-a83a-d6af5d42b919",
            "id_usuario": "64cc6794-0d36-4074-a037-4d99c4c1a53c",
            "nome": "Three Cheers... - CD",
            "valor": 5960,
            "condicao": "Ótimo",
            "descricao": "CD bem conservado, faço teste antes do pagamento",
            "artista": "My Chemical Romance",
            "ano": 2004,
            "gravadora": "Reprise Records"
        },
        {
            "id_prod": "65b991b3-ff00-4b26-802c-4903af87c95a",
            "id_usuario": "2b6b0204-edcf-4963-9562-b9d3ff07641d",
            "nome": "Ciano - Vinil",
            "valor": 23000,
            "condicao": "Bom",
            "descricao": "Capa do vinil está um pouco descascada, fora isso, o disco está intacto",
            "artista": "Fresno",
            "ano": 2006,
            "gravadora": "BMG"
        },
        {
            "id_prod": "5b26715b-b98a-4c28-971c-79c8d5006b5f",
            "id_usuario": "3f988b44-a034-45e0-9e6b-07b949b28b74",
            "nome": "Xou da Xuxa - Vinil",
            "valor": 58600,
            "condicao": "Bom",
            "descricao": "Amarelado pela idade, mas o disco funciona perfeitamente",
            "artista": "Xuxa",
            "ano": 1986,
            "gravadora": "Som Livre"
        },
        {
            "id_prod": "3d9a6328-91c6-48f8-b397-6a5639d6b553",
            "id_usuario": "04017639-688d-4a1d-a99b-d7b686259048",
            "nome": "Não Deixe o Samba Morrer - Vinil",
            "valor": 3290,
            "descricao": "Excelente estado",
            "artista": "Alcione",
            "condicao": "Excelente",
            "ano": 1975,
            "gravadora": "Sony"
        }
    ],
    "livro": [
        {
            "id_prod": "9c8a9018-b80c-4394-a1e6-0be63d919830",
            "id_usuario": "8f3075c3-b45b-432a-a9e9-0639d73d63c4",
            "nome": "Crime e Castigo",
            "valor": 2390,
            "condicao": "Bom - Manchas",
            "descricao": "Possui algumas manchas amareladas nas páginas devido à velhice, sem rasgos ou avarias maiores",
            "autor": "Fiódor Dostoiévski",
            "edicao": "5° - Antofágica",
            "qtd_pag": 592
        },
        {
            "id_prod": "b8f4133f-9118-4a94-b258-29471138883b",
            "id_usuario": "2b6b0204-edcf-4963-9562-b9d3ff07641d",
            "nome": "Quarta Asa",
            "valor": 4590,
            "condicao": "Excelente",
            "descricao": "Em estado de novo, venda por motivo de mudança",
            "autor": "Rebecca Yarros",
            "edicao": "2° - Planeta Minotauro",
            "qtd_pag": 544
        },
        {
            "id_prod": "6d729e2f-515a-471a-85d2-06858e5d0a64",
            "id_usuario": "64cc6794-0d36-4074-a037-4d99c4c1a53c",
            "nome": "A Canção de Aquiles",
            "valor": 2260,
            "condicao": "Avariado",
            "descricao": "Possui marcas de uso na capa, como arranhões e amassados",
            "autor": "Madeline Miller",
            "edicao": "3° - Planeta Minotauro",
            "qtd_pag": 392
        },
        {
            "id_prod": "8c59f0f9-a29d-4034-8b63-c77f2824707e",
            "id_usuario": "8f3075c3-b45b-432a-a9e9-0639d73d63c4",
            "nome": "O Hobbit",
            "valor": 2830,
            "condicao": "Excelente",
            "descricao": "Sem danos",
            "autor": "J.R.R Tolkien",
            "edicao": "3° - Harper Collins Brasil",
            "qtd_pag": 331
        },
        {
            "id_prod": "f51953ce-0c1f-4ffb-8f3a-592f036720d2",
            "id_usuario": "04017639-688d-4a1d-a99b-d7b686259048",
            "nome": "Torto Arado",
            "valor": 3010,
            "condicao": "Excelente",
            "descricao": "Sem danos",
            "autor": "Itamar Vieira Junior",
            "edicao": "1° - Todavia",
            "qtd_pag": 331
        }
    ],
    "palavra_chave": [
        {
            "nome": "rock"
        },
        {
            "nome": "fantasia"
        },
        {
            "nome": "romance"
        },
        {
            "nome": "queen"
        },
        {
            "nome": "mcr"
        },
        {
            "nome": "fresno"
        },
        {
            "nome": "indie"
        },
        {
            "nome": "xuxa"
        },
        {
            "nome": "alternativo"
        },
        {
            "nome": "pop"
        },
        {
            "nome": "emo"
        },
        {
            "nome": "clássicos"
        },
        {
            "nome": "literatura russa"
        },
        {
            "nome": "alta fantasia"
        },
        {
            "nome": "mitologia grega"
        },
        {
            "nome": "releituras"
        },
        {
            "nome": "tolkien"
        },
        {
            "nome": "fiódor dostoiésvski"
        },
        {
            "nome": "infantil"
        },
        {
            "nome": "infanto-juvenil"
        },
        {
            "nome": "público maduro"
        },
        {
            "nome": "rock clássico"
        },
        {
            "nome": "dragões"
        }
    ],
    "palavra_disco": [
        {
            "prod": "0f63ff4e-73e4-4a29-b611-3968e0d68800",
            "nome": "rock"
        },
        {
            "prod": "0f63ff4e-73e4-4a29-b611-3968e0d68800",
            "nome": "queen"
        },
        {
            "prod": "0f63ff4e-73e4-4a29-b611-3968e0d68800",
            "nome": "rock clássico"
        },
        {
            "prod": "136359f1-332e-4b71-a83a-d6af5d42b919",
            "nome": "rock"
        },
        {
            "prod": "136359f1-332e-4b71-a83a-d6af5d42b919",
            "nome": "mcr"
        },
        {
            "prod": "136359f1-332e-4b71-a83a-d6af5d42b919",
            "nome": "alternativo"
        },
        {
            "prod": "136359f1-332e-4b71-a83a-d6af5d42b919",
            "nome": "emo"
        },
        {
            "prod": "136359f1-332e-4b71-a83a-d6af5d42b919",
            "nome": "público maduro"
        },
        {
            "prod": "65b991b3-ff00-4b26-802c-4903af87c95a",
            "nome": "rock"
        },
        {
            "prod": "65b991b3-ff00-4b26-802c-4903af87c95a",
            "nome": "fresno"
        },
        {
            "prod": "65b991b3-ff00-4b26-802c-4903af87c95a",
            "nome": "indie"
        },
        {
            "prod": "65b991b3-ff00-4b26-802c-4903af87c95a",
            "nome": "alternativo"
        },
        {
            "prod": "65b991b3-ff00-4b26-802c-4903af87c95a",
            "nome": "emo"
        },
        {
            "prod": "5b26715b-b98a-4c28-971c-79c8d5006b5f",
            "nome": "xuxa"
        },
        {
            "prod": "5b26715b-b98a-4c28-971c-79c8d5006b5f",
            "nome": "pop"
        },
        {
            "prod": "5b26715b-b98a-4c28-971c-79c8d5006b5f",
            "nome": "infantil"
        },
        {
            "prod": "5b26715b-b98a-4c28-971c-79c8d5006b5f",
            "nome": "infanto-juvenil"
        }
    ],
    "palavra_livro": [
        {
            "prod": "f51953ce-0c1f-4ffb-8f3a-592f036720d2",
            "nome": "clássicos"
        },
        {
            "prod": "f51953ce-0c1f-4ffb-8f3a-592f036720d2",
            "nome": "literatura russa"
        },
        {
            "prod": "f51953ce-0c1f-4ffb-8f3a-592f036720d2",
            "nome": "fiodór dostoiésvski"
        },
        {
            "prod": "f51953ce-0c1f-4ffb-8f3a-592f036720d2",
            "nome": "público maduro"
        },
        {
            "prod": "b8f4133f-9118-4a94-b258-29471138883b",
            "nome": "fantasia"
        },
        {
            "prod": "b8f4133f-9118-4a94-b258-29471138883b",
            "nome": "romance"
        },
        {
            "prod": "b8f4133f-9118-4a94-b258-29471138883b",
            "nome": "alta fantasia"
        },
        {
            "prod": "b8f4133f-9118-4a94-b258-29471138883b",
            "nome": "dragões"
        },
        {
            "prod": "6d729e2f-515a-471a-85d2-06858e5d0a64",
            "nome": "fantasia"
        },
        {
            "prod": "6d729e2f-515a-471a-85d2-06858e5d0a64",
            "nome": "romance"
        },
        {
            "prod": "6d729e2f-515a-471a-85d2-06858e5d0a64",
            "nome": "mitologia grega"
        },
        {
            "prod": "6d729e2f-515a-471a-85d2-06858e5d0a64",
            "nome": "releituras"
        },
        {
            "prod": "8c59f0f9-a29d-4034-8b63-c77f2824707e",
            "nome": "fantasia"
        },
        {
            "prod": "8c59f0f9-a29d-4034-8b63-c77f2824707e",
            "nome": "alta fantasia"
        },
        {
            "prod": "8c59f0f9-a29d-4034-8b63-c77f2824707e",
            "nome": "clássicos"
        },
        {
            "prod": "8c59f0f9-a29d-4034-8b63-c77f2824707e",
            "nome": "tolkien"
        },
        {
            "prod": "8c59f0f9-a29d-4034-8b63-c77f2824707e",
            "nome": "infanto-juvenil"
        },
        {
            "prod": "8c59f0f9-a29d-4034-8b63-c77f2824707e",
            "nome": "dragões"
        }
    ],
    "palavra_usuario": [
        {
            "usuario": "3f988b44-a034-45e0-9e6b-07b949b28b74",
            "nome": "rock"
        },
        {
            "usuario": "3f988b44-a034-45e0-9e6b-07b949b28b74",
            "nome": "mcr"
        },
        {
            "usuario": "3f988b44-a034-45e0-9e6b-07b949b28b74",
            "nome": "indie"
        },
        {
            "usuario": "3f988b44-a034-45e0-9e6b-07b949b28b74",
            "nome": "alternativo"
        },
        {
            "usuario": "3f988b44-a034-45e0-9e6b-07b949b28b74",
            "nome": "xuxa"
        },
        {
            "usuario": "3f988b44-a034-45e0-9e6b-07b949b28b74",
            "nome": "literatura russa"
        },
        {
            "usuario": "2b6b0204-edcf-4963-9562-b9d3ff07641d",
            "nome": "alta fantasia"
        },
        {
            "usuario": "2b6b0204-edcf-4963-9562-b9d3ff07641d",
            "nome": "romance"
        },
        {
            "usuario": "2b6b0204-edcf-4963-9562-b9d3ff07641d",
            "nome": "fresno"
        },
        {
            "usuario": "2b6b0204-edcf-4963-9562-b9d3ff07641d",
            "nome": "pop"
        },
        {
            "usuario": "2b6b0204-edcf-4963-9562-b9d3ff07641d",
            "nome": "infanto-juvenil"
        },
        {
            "usuario": "2b6b0204-edcf-4963-9562-b9d3ff07641d",
            "nome": "dragões"
        },
        {
            "usuario": "04017639-688d-4a1d-a99b-d7b686259048",
            "nome": "fantasia"
        },
        {
            "usuario": "04017639-688d-4a1d-a99b-d7b686259048",
            "nome": "romance"
        },
        {
            "usuario": "04017639-688d-4a1d-a99b-d7b686259048",
            "nome": "indie"
        },
        {
            "usuario": "04017639-688d-4a1d-a99b-d7b686259048",
            "nome": "clássicos"
        },
        {
            "usuario": "04017639-688d-4a1d-a99b-d7b686259048",
            "nome": "mitologia grega"
        },
        {
            "usuario": "8f3075c3-b45b-432a-a9e9-0639d73d63c4",
            "nome": "rock"
        },
        {
            "usuario": "8f3075c3-b45b-432a-a9e9-0639d73d63c4",
            "nome": "queen"
        },
        {
            "usuario": "8f3075c3-b45b-432a-a9e9-0639d73d63c4",
            "nome": "literatura russa"
        },
        {
            "usuario": "8f3075c3-b45b-432a-a9e9-0639d73d63c4",
            "nome": "tolkien"
        },
        {
            "usuario": "8f3075c3-b45b-432a-a9e9-0639d73d63c4",
            "nome": "fiódor dostoiésvski"
        },
        {
            "usuario": "64cc6794-0d36-4074-a037-4d99c4c1a53c",
            "nome": "rock"
        },
        {
            "usuario": "64cc6794-0d36-4074-a037-4d99c4c1a53c",
            "nome": "mcr"
        },
        {
            "usuario": "64cc6794-0d36-4074-a037-4d99c4c1a53c",
            "nome": "alternativo"
        },
        {
            "usuario": "64cc6794-0d36-4074-a037-4d99c4c1a53c",
            "nome": "emo"
        },
        {
            "usuario": "64cc6794-0d36-4074-a037-4d99c4c1a53c",
            "nome": "literatura russa"
        }
    ],
    "segue": [
        {
            "seguinte": "3f988b44-a034-45e0-9e6b-07b949b28b74",
            "seguido": "2b6b0204-edcf-4963-9562-b9d3ff07641d"
        },
        {
            "seguinte": "3f988b44-a034-45e0-9e6b-07b949b28b74",
            "seguido": "04017639-688d-4a1d-a99b-d7b686259048"
        },
        {
            "seguinte": "2b6b0204-edcf-4963-9562-b9d3ff07641d",
            "seguido": "8f3075c3-b45b-432a-a9e9-0639d73d63c4"
        },
        {
            "seguinte": "04017639-688d-4a1d-a99b-d7b686259048",
            "seguido": "3f988b44-a034-45e0-9e6b-07b949b28b74"
        },
        {
            "seguinte": "8f3075c3-b45b-432a-a9e9-0639d73d63c4",
            "seguido": "64cc6794-0d36-4074-a037-4d99c4c1a53c"
        },
        {
            "seguinte": "64cc6794-0d36-4074-a037-4d99c4c1a53c",
            "seguido": "04017639-688d-4a1d-a99b-d7b686259048"
        }
    ],
    "usuario": [
        {
            "cod": "3f988b44-a034-45e0-9e6b-07b949b28b74",
            "nome": "Emanuel Dionisio",
            "tel1": "(83) 99830-7031",
            "tel2": null,
            "email": "emanuel.eduardo@academico.ifpb.edu.br",
            "dt_nascimento": "2007-12-17T00:00:00.000Z",
            "pais": "Brasil",
            "estado": "Bahia",
            "cidade": "Xique-Xique",
            "bairro": "Jacarezinho do norte",
            "rua": "Rua Aposentada dos Tolos",
            "senha": "krobus123",
            "num_casa": 215,
            "foto_perfil": "1.jpg"
        },
        {
            "cod": "2b6b0204-edcf-4963-9562-b9d3ff07641d",
            "nome": "Samarinha",
            "tel1": "(83) 99352-8767",
            "tel2": null,
            "email": "alice.batista@academico.ifpb.edu.br",
            "dt_nascimento": "2007-09-07T00:00:00.000Z",
            "pais": "Brasil",
            "estado": "Paraíba",
            "cidade": "João Pessoa",
            "bairro": "Geisel",
            "rua": "Rua Passarinho Bem-te-vi da Silva Assobiante",
            "senha": "alicinhagamer",
            "num_casa": 479,
            "foto_perfil": "2.jpg"
        },
        {
            "cod": "04017639-688d-4a1d-a99b-d7b686259048",
            "nome": "Manuca",
            "tel1": "(83) 98398-8428",
            "tel2": null,
            "email": "emanuele.targino@academico.ifpb.edu.br",
            "dt_nascimento": "2007-05-21T00:00:00.000Z",
            "pais": "Brasil",
            "estado": "Paraíba",
            "cidade": "João Pessoa",
            "bairro": "Treze de Maio",
            "rua": "Rua Samba Potente que Desce no Pé",
            "senha": "manuzinhadogera",
            "num_casa": 791,
            "foto_perfil": "3.jpg"
        },
        {
            "cod": "8f3075c3-b45b-432a-a9e9-0639d73d63c4",
            "nome": "Çãm",
            "tel1": "(83) 99404-6168",
            "tel2": null,
            "email": "samuel.linhares@academico.ifpb.edu.br",
            "dt_nascimento": "2007-11-14T00:00:00.000Z",
            "pais": "Brasil",
            "estado": "Paraíba",
            "cidade": "João Pessoa",
            "bairro": "José Américo",
            "rua": "Rua Padrinho Chico Xavier Astrólogo",
            "senha": "RatoQueRoeuARoupaDoRei",
            "num_casa": 331,
            "foto_perfil": "4.jpg"
        },
        {
            "cod": "64cc6794-0d36-4074-a037-4d99c4c1a53c",
            "nome": "Oliveira",
            "tel1": "(83) 94334-7790",
            "tel2": null,
            "email": "rodrigues.luzia@academico.ifpb.edu.br",
            "dt_nascimento": "2007-08-01T00:00:00.000Z",
            "pais": "Brasil",
            "estado": "Paraíba",
            "cidade": "João Pessoa",
            "bairro": "Bancários",
            "rua": "Rua Banqueiros em Protesto por Aumento Salarial",
            "senha": "brocedes644",
            "num_casa": 414,
            "foto_perfil": "5.jpg"
        }
    ]
}